ABOUT.rst
CHANGES.rst
COPYRIGHT.txt
LICENSE.txt
README.rst
base.cfg
index.txt
setup.py
tox.ini
doc/about.txt
doc/conf.py
doc/modules.txt
doc/tests.txt
src/tl/__init__.py
src/tl.eggdeps.egg-info/PKG-INFO
src/tl.eggdeps.egg-info/SOURCES.txt
src/tl.eggdeps.egg-info/dependency_links.txt
src/tl.eggdeps.egg-info/entry_points.txt
src/tl.eggdeps.egg-info/namespace_packages.txt
src/tl.eggdeps.egg-info/not-zip-safe
src/tl.eggdeps.egg-info/requires.txt
src/tl.eggdeps.egg-info/top_level.txt
src/tl/eggdeps/__init__.py
src/tl/eggdeps/cli.py
src/tl/eggdeps/dot.py
src/tl/eggdeps/dot.txt
src/tl/eggdeps/graph.py
src/tl/eggdeps/graph.txt
src/tl/eggdeps/plaintext.py
src/tl/eggdeps/plaintext.txt
src/tl/eggdeps/regressions.txt
src/tl/eggdeps/requirements.py
src/tl/eggdeps/requirements.txt
src/tl/eggdeps/tests.py