Metadata-Version: 2.1
Name: tl.eggdeps
Version: 1.0
Summary: Compute a dependency graph between active Python eggs.
Home-page: https://github.com/tlotze/tl.eggdeps
Author: Thomas Lotze
Author-email: thomas@thomas-lotze.de
License: ZPL 2.1
Keywords: egg eggs dependencies dependency graph tree
Platform: UNKNOWN
Classifier: Development Status :: 3 - Alpha
Classifier: Environment :: Console
Classifier: Intended Audience :: Developers
Classifier: Intended Audience :: System Administrators
Classifier: License :: OSI Approved :: Zope Public License
Classifier: Programming Language :: Python
Classifier: Programming Language :: Python :: 3 :: Only
Classifier: Programming Language :: Python :: 3.7
Classifier: Programming Language :: Python :: 3.8
Classifier: Programming Language :: Python :: Implementation :: CPython
Classifier: Topic :: Software Development
Classifier: Topic :: Utilities
Requires-Python: >=3.7, <4
Provides-Extra: test
